{
  "stoneAxe": {
    "name": "Stone Axe",
    "description": "A bit rusty but still can cut some trees",
    "price": 75,
    "attackValue": 1,
    "knockbackValue": 8,
    "texturePath": "textures/entity/items/stone_axe.png",
    "spriteSheetPath": "textures/entity/items/stone_axe_frame.png"
  },
  "boots": {
    "name": "Boots",
    "texturePath": "textures/entity/items/boots.png"
  },
  "chest": {
    "name": "Chest",
    "solid": true,
    "frameWidth": 32,
    "frameHeight": 32,
    "frameScale": 1,
    "spriteSheetPath": "textures/entity/items/chest.png"
  },
  "chicken": {
    "name": "Chicken",
    "description": "Yes...\nLizard's treasure",
    "price": 1,
    "texturePath": "textures/entity/items/chicken.png"
  },
  "woodDoor": {
    "name": "Wood Door",
    "solid": true,
    "texturePath": "textures/entity/items/wood_door.png"
  },
  "ironDoor": {
    "name": "Iron Door",
    "solid": true,
    "texturePath": "textures/entity/items/door_iron.png"
  },
  "gold": {
    "name": "Gold",
    "stackable": true,
    "texturePath": "textures/entity/items/gold.png"
  },
  "key": {
    "name": "Key",
    "description": "It opens a door",
    "texturePath": "textures/entity/items/key.png"
  },
  "lantern": {
    "name": "Lantern",
    "description": "Illuminates your surroundings",
    "price": 45,
    "lightRadius": 350,
    "texturePath": "textures/entity/items/lantern.png"
  },
  "stonePickaxe": {
    "name": "Stone Pickaxe",
    "description": "You will dig it!",
    "sound": "drawPickaxe",
    "price": 60,
    "attackValue": 1,
    "knockbackValue": 8,
    "texturePath": "textures/entity/items/stone_pickaxe.png",
    "spriteSheetPath": "textures/entity/items/stone_pickaxe_frame.png"
  },
  "potionBlue": {
    "name": "Blue Potion",
    "description": "Increase your mana by {points}",
    "price": 4,
    "points": 2,
    "stackable": true,
    "texturePath": "textures/entity/items/potion_blue.png"
  },
  "potionRed": {
    "name": "Red Potion",
    "description": "Heals your life by {points}",
    "price": 2,
    "points": 2,
    "stackable": true,
    "texturePath": "textures/entity/items/potion_red.png"
  },
  "ironShield": {
    "name": "Iron Shield",
    "description": "A shiny iron shield",
    "price": 250,
    "defenseValue": 2,
    "texturePath": "textures/entity/items/iron_shield.png"
  },
  "woodShield": {
    "name": "Wood Shield",
    "description": "Made by wood",
    "price": 150,
    "defenseValue": 1,
    "texturePath": "textures/entity/items/wood_shield.png"
  },
  "stone": {
    "name": "Stone",
    "description": "It's just a stone",
    "price": 7,
    "stackable": true,
    "texturePath": "textures/entity/items/stone.png"
  },
  "stoneSword": {
    "name": "Stone Sword",
    "description": "An old sword",
    "sound": "drawSword",
    "price": 20,
    "attackValue": 1,
    "knockbackValue": 2,
    "texturePath": "textures/entity/items/stone_sword.png",
    "spriteSheetPath": "textures/entity/items/stone_sword_frame.png"
  },
  "tent": {
    "name": "Tent",
    "description": "You can sleep until next morning",
    "price": 380,
    "texturePath": "textures/entity/items/tent.png"
  },
  "wood": {
    "name": "Wood",
    "description": "Forest wood",
    "price": 5,
    "stackable": true,
    "texturePath": "textures/entity/items/wood.png"
  }
}
